{
  "type": "FeatureCollection",
  "features": [
    {
      "type": "Feature",
      "properties": {},
      "geometry": {
        "type": "Polygon",
        "coordinates": [
          [
            [
              13.674287796020506,
              51.07257620730564
            ],
            [
              13.675661087036133,
              51.06723678308614
            ],
            [
              13.676004409790039,
              51.06313741319562
            ],
            [
              13.674888610839844,
              51.05585474252802
            ],
            [
              13.674545288085938,
              51.05008173789145
            ],
            [
              13.679695129394531,
              51.04878675953189
            ],
            [
              13.677892684936523,
              51.04387630433032
            ],
            [
              13.676004409790039,
              51.04182563049972
            ],
            [
              13.681583404541016,
              51.03551114368058
            ],
            [
              13.686561584472656,
              51.03529524857577
            ],
            [
              13.696689605712889,
              51.03340612350169
            ],
            [
              13.697547912597656,
              51.03124702911513
            ],
            [
              13.702783584594727,
              51.02784625147744
            ],
            [
              13.709306716918944,
              51.02125990909237
            ],
            [
              13.716344833374023,
              51.017750410136486
            ],
            [
              13.727760314941406,
              51.016400532111504
            ],
            [
              13.73960494995117,
              51.01407864998378
            ],
            [
              13.741922378540039,
              51.00975855992484
            ],
            [
              13.759260177612305,
              51.004249861455264
            ],
            [
              13.76483917236328,
              51.00451991094253
            ],
            [
              13.770074844360352,
              51.00651822828961
            ],
            [
              13.787670135498047,
              51.01299866519572
            ],
            [
              13.7933349609375,
              51.0191542415962
            ],
            [
              13.799171447753906,
              51.02158384944998
            ],
            [
              13.799686431884766,
              51.025848853062705
            ],
            [
              13.804922103881834,
              51.02995152419996
            ],
            [
              13.810586929321289,
              51.033837930308316
            ],
            [
              13.814105987548828,
              51.03901929815593
            ],
            [
              13.817367553710938,
              51.04328269755669
            ],
            [
              13.81204605102539,
              51.051538545266844
            ],
            [
              13.817882537841797,
              51.05396645572719
            ],
            [
              13.814706802368164,
              51.055800792545135
            ],
            [
              13.807668685913086,
              51.05423621569879
            ],
            [
              13.800287246704102,
              51.05855216152903
            ],
            [
              13.790159225463865,
              51.060602094874234
            ],
            [
              13.778486251831053,
              51.06173491383668
            ],
            [
              13.778057098388672,
              51.06410834940008
            ],
            [
              13.776254653930664,
              51.07031107226295
            ],
            [
              13.768186569213867,
              51.07333122768277
            ],
            [
              13.758831024169922,
              51.07667474128143
            ],
            [
              13.752908706665039,
              51.07840033119636
            ],
            [
              13.750677108764648,
              51.078022863901595
            ],
            [
              13.74835968017578,
              51.079209179315455
            ],
            [
              13.739776611328125,
              51.0878360127544
            ],
            [
              13.733768463134764,
              51.09080111518889
            ],
            [
              13.727588653564453,
              51.095221460388174
            ],
            [
              13.722352981567383,
              51.09678465206282
            ],
            [
              13.714971542358398,
              51.097485376003554
            ],
            [
              13.70595932006836,
              51.09619172351068
            ],
            [
              13.698577880859373,
              51.09252617822148
            ],
            [
              13.695230484008789,
              51.09268789958169
            ],
            [
              13.691883087158203,
              51.088536872303806
            ],
            [
              13.687334060668945,
              51.079856247629635
            ],
            [
              13.674287796020506,
              51.07257620730564
            ]
          ]
        ]
      }
    }
  ]
}
